flask_stats/__init__.py
flask_stats/debug_context.py
flask_stats/debug_decorator.py
flask_stats/flask_stats.py
flask_stats/record_request.py
flask_stats/sqlite_repository.py
flask_stats/time_context.py
flask_stats/time_decorator.py
tests/__init__.py
tests/flask_app.py
tests/test_uptime.py
flask_api_stats-0.5.dist-info/LICENSE
flask_api_stats-0.5.dist-info/METADATA
flask_api_stats-0.5.dist-info/WHEEL
flask_api_stats-0.5.dist-info/top_level.txt
flask_api_stats-0.5.dist-info/RECORD
