Metadata-Version: 2.1
Name: flask-api-stats
Version: 0.5
Summary: A plugin for flask to obtain API statistics
Home-page: https://github.com/Gaturron/flask-stats
Author: Fernando Bugni
Author-email: fernando.bugni@gmail.com
License: UNKNOWN
Platform: UNKNOWN
Classifier: Programming Language :: Python :: 3
Classifier: License :: OSI Approved :: MIT License
Classifier: Operating System :: OS Independent
